annolid/__init__.py
annolid/features.py
annolid/main.py
annolid/agents/__init__.py
annolid/agents/behavior_agent.py
annolid/agents/chatterbox_tts.py
annolid/agents/frame_embedder.py
annolid/agents/frame_search.py
annolid/agents/kokoro_tts.py
annolid/agents/speech_recognition.py
annolid/agents/tts_router.py
annolid/annotation/__init__.py
annolid/annotation/coco2deeplabcut.py
annolid/annotation/coco2labelme.py
annolid/annotation/coco2yolo.py
annolid/annotation/davis_dataset_converter.py
annolid/annotation/deeplabcut2labelme.py
annolid/annotation/detections_writer.py
annolid/annotation/events.py
annolid/annotation/fix_shapes.py
annolid/annotation/keypoint_visibility.py
annolid/annotation/keypoints.py
annolid/annotation/label_processor.py
annolid/annotation/labelme.md
annolid/annotation/labelme2binarymasks.py
annolid/annotation/labelme2coco.py
annolid/annotation/labelme2csv.py
annolid/annotation/labelme2yolo.py
annolid/annotation/labels.txt
annolid/annotation/labels_custom.txt
annolid/annotation/labels_interaction
annolid/annotation/mabe_2022_labels.txt
annolid/annotation/masks.py
annolid/annotation/mot2coco.py
annolid/annotation/polygons.py
annolid/annotation/pose_schema.py
annolid/annotation/qvheighlights.py
annolid/annotation/sanitize_labelme_json.py
annolid/annotation/sleap2labelme.py
annolid/annotation/timestamps.py
annolid/behavior/__init__.py
annolid/behavior/config.py
annolid/behavior/ethogram.py
annolid/behavior/evaluation.py
annolid/behavior/event_utils.py
annolid/behavior/inference.py
annolid/behavior/pipeline.py
annolid/behavior/project_schema.py
annolid/behavior/prompting.py
annolid/behavior/time_budget.py
annolid/behavior/data_loading/__init__.py
annolid/behavior/data_loading/datasets.py
annolid/behavior/data_loading/multimodal_data.py
annolid/behavior/data_loading/transforms.py
annolid/behavior/data_loading/video_splitter.py
annolid/behavior/models/__init__.py
annolid/behavior/models/classifier.py
annolid/behavior/models/feature_extractors.py
annolid-1.4.0.dist-info/licenses/LICENSE
annolid-1.4.0.dist-info/METADATA
annolid-1.4.0.dist-info/WHEEL
annolid-1.4.0.dist-info/entry_points.txt
annolid-1.4.0.dist-info/top_level.txt
annolid-1.4.0.dist-info/RECORD
