Metadata-Version: 2.4
Name: annolid
Version: 1.4.0
Summary: An annotation and instance segmentation-based multiple animal tracking and behavior analysis package.
Author-email: Chen Yang <healthonrails@gmail.com>
License-Expression: CC-BY-NC-4.0
Project-URL: Homepage, https://github.com/healthonrails/annolid
Project-URL: Repository, https://github.com/healthonrails/annolid
Classifier: Programming Language :: Python :: 3
Classifier: Programming Language :: Python :: 3.10
Classifier: Programming Language :: Python :: 3.11
Classifier: Programming Language :: Python :: 3.12
Classifier: Programming Language :: Python :: 3.13
Classifier: Operating System :: OS Independent
Requires-Python: >=3.10
License-File: LICENSE
Requires-Dist: numpy<2.0,>=1.24
Requires-Dist: scipy>=1.5.2
Requires-Dist: easydict>=1.9
Requires-Dist: opencv-contrib-python>=4.1.2.30
Requires-Dist: PyYAML>=5.3
Requires-Dist: labelme==5.5.0
Requires-Dist: sounddevice>=0.4.6
Requires-Dist: librosa>=0.10.1
Requires-Dist: torch>=2.4.0
Requires-Dist: torchvision>=0.19.0
Requires-Dist: pandas>=1.1.3
Requires-Dist: pycocotools>=2.0.2
Requires-Dist: tensorboard>=2.3.0
Requires-Dist: imageio>=2.8.0
Requires-Dist: tqdm>=4.64.0
Requires-Dist: shapely>=2.0.2
Requires-Dist: imageio-ffmpeg>=0.4.2
Requires-Dist: qimage2ndarray>=1.8
Requires-Dist: tokenizers
Requires-Dist: einops>=0.6
Requires-Dist: omegaconf>=2.3.0
Requires-Dist: hydra-core>=1.3.2
Requires-Dist: timm>=0.9.7
Requires-Dist: h5py>=3.10.0
Requires-Dist: psutil>=5.9.8
Requires-Dist: pyserial>=3.5
Requires-Dist: pyzmq>=25.1.2
Requires-Dist: ffpyplayer>=4.5.0
Requires-Dist: tree-config>=0.6.0
Requires-Dist: Pillow<12.0,>=9.3.0
Requires-Dist: chardet>=5.2.0
Requires-Dist: transformers>=4.45.1
Requires-Dist: ultralytics>=8.4.0
Requires-Dist: huggingface-hub>=0.22.0
Requires-Dist: tensorboard
Provides-Extra: sam3
Requires-Dist: iopath>=0.1.9; extra == "sam3"
Requires-Dist: ftfy>=6.1.1; extra == "sam3"
Provides-Extra: image-editing
Requires-Dist: diffusers>=0.32.0; extra == "image-editing"
Requires-Dist: accelerate>=0.27.0; extra == "image-editing"
Requires-Dist: safetensors>=0.4.0; extra == "image-editing"
Dynamic: license-file
